CHANGELOG.md
LICENSE
MANIFEST.in
README.md
setup.py
plistutils/__init__.py
plistutils/alias.py
plistutils/bookmark.py
plistutils/nskeyedarchiver.py
plistutils/plistparser.py
plistutils/utils.py
plistutils.egg-info/PKG-INFO
plistutils.egg-info/SOURCES.txt
plistutils.egg-info/dependency_links.txt
plistutils.egg-info/requires.txt
plistutils.egg-info/top_level.txt