Metadata-Version: 1.1
Name: plistutils
Version: 1.0.0
Summary: Convenience functions for plist files
Home-page: https://github.com/strozfriedberg/plistutils
Author: Stroz Friedberg, an Aon company
Author-email: UNKNOWN
License: BSD 3-clause "New" or "Revised" License
Keywords: plist apple mac
Platform: UNKNOWN
Classifier: Development Status :: 5 - Production/Stable
Classifier: Intended Audience :: Developers
Classifier: Topic :: Software Development :: Build Tools
Classifier: License :: OSI Approved :: BSD License
Classifier: Operating System :: OS Independent
Classifier: Programming Language :: Python :: 3
Classifier: Programming Language :: Python :: 3.5
Classifier: Topic :: Software Development :: Libraries :: Python Modules
